Playwright/__init__.py
robotframework_playwright-0.1.0.dist-info/LICENSE
robotframework_playwright-0.1.0.dist-info/WHEEL
robotframework_playwright-0.1.0.dist-info/METADATA
robotframework_playwright-0.1.0.dist-info/RECORD
